{
	"name":"BDC抑郁症自我诊断表",
	"description":"美国新一代心理治疗专家、宾夕法尼亚大学的David D·Burns博士设计出一套抑郁症的自我诊断表“伯恩斯抑郁症清单（BDC）”，这个自我诊断表可帮助你快速诊断出你是否存在着抑郁症。\n请选择符合你情绪的项：没有，轻度，中度，严重",
	"objects":[
		{"text":"悲伤：你是否一直感到伤心或悲哀？","choice":{"没有":0,"轻度":1,"中度":2,"严重":3}},
		{"text":"泄气：你是否感到前景渺茫？","choice":{"没有":0,"轻度":1,"中度":2,"严重":3}},
		{"text":"缺乏自尊：你是否觉得自己没有价值或自以为是一个失败者？","choice":{"没有":0,"轻度":1,"中度":2,"严重":3}},
		{"text":"自卑：你是否觉得力不从心或自叹比不上别人？","choice":{"没有":0,"轻度":1,"中度":2,"严重":3}},
		{"text":"内疚：你是否对任何事都自责？","choice":{"没有":0,"轻度":1,"中度":2,"严重":3}},
		{"text":"犹豫：你是否在做决定时犹豫不决？","choice":{"没有":0,"轻度":1,"中度":2,"严重":3}},
		{"text":"焦躁不安：这段时间你是否一直处于愤怒和不满状态？","choice":{"没有":0,"轻度":1,"中度":2,"严重":3}},
		{"text":"对生活丧失兴趣：你对事业、家庭、爱好或朋友是否丧失了兴趣？","choice":{"没有":0,"轻度":1,"中度":2,"严重":3}},
		{"text":"丧失动机：你是否感到一蹶不振做事情毫无动力？","choice":{"没有":0,"轻度":1,"中度":2,"严重":3}},
		{"text":"自我印象可怜：你是否以为自己已衰老或失去魅力？","choice":{"没有":0,"轻度":1,"中度":2,"严重":3}},
		{"text":"食欲变化：你是否感到食欲不振或情不自禁地暴饮暴食？","choice":{"没有":0,"轻度":1,"中度":2,"严重":3}},
		{"text":"睡眠变化：你是否患有失眠症或整天感到体力不支、昏昏欲睡？","choice":{"没有":0,"轻度":1,"中度":2,"严重":3}},
		{"text":"丧失性欲：你是否丧失了对性的兴趣？","choice":{"没有":0,"轻度":1,"中度":2,"严重":3}},
		{"text":"臆想症：你是否经常担心自己的健康？","choice":{"没有":0,"轻度":1,"中度":2,"严重":3}},
		{"text":"自杀冲动：你是否认为生存没有价值，或生不如死？","choice":{"没有":0,"轻度":1,"中度":2,"严重":3}}
	],
	"random":true,
	"results":{
		"0,4":"没有抑郁",
		"5,10":"偶尔有忧郁情绪",
		"11,20":"轻度抑郁",
		"21,30":"中等抑郁",
		"31,45":"严重抑郁"
	}
}